consul/__init__.py
consul/aio.py
consul/base.py
consul/callback.py
consul/check.py
consul/exceptions.py
consul/std.py
consul/api/__init__.py
consul/api/agent.py
consul/api/catalog.py
consul/api/connect.py
consul/api/coordinates.py
consul/api/event.py
consul/api/health.py
consul/api/kv.py
consul/api/operator.py
consul/api/query.py
consul/api/session.py
consul/api/status.py
consul/api/txn.py
consul/api/acl/__init__.py
consul/api/acl/policy.py
consul/api/acl/token.py
docs/__init__.py
docs/conf.py
py_consul-1.6.0.data/data/requirements.txt
py_consul-1.6.0.data/data/tests-requirements.txt
py_consul-1.6.0.dist-info/licenses/LICENSE
py_consul-1.6.0.dist-info/METADATA
py_consul-1.6.0.dist-info/WHEEL
py_consul-1.6.0.dist-info/top_level.txt
py_consul-1.6.0.dist-info/RECORD
